irflow_client/__init__.py
irflow_client/__version__.py
irflow_client/irflow_client.py
irflow_client-1.6.3.dist-info/LICENSE.txt
irflow_client-1.6.3.dist-info/METADATA
irflow_client-1.6.3.dist-info/WHEEL
irflow_client-1.6.3.dist-info/top_level.txt
irflow_client-1.6.3.dist-info/RECORD
