Metadata-Version: 2.1
Name: irflow-client
Version: 1.6.3
Summary: A python client for Syncurity IR-Flow
Home-page: https://syncurity.net
Author: Syncurity
Author-email: support@syncurity.net
Maintainer: Syncurity Corp.
Maintainer-email: support@syncurity.net
License: Apache 2.0
Keywords: Syncurity syncurity IR-Flow ir-flow irflow security incident response
Platform: Windows
Platform: MacOS
Platform: Enterprise Linux
Classifier: Development Status :: 5 - Production/Stable
Classifier: Intended Audience :: Developers
Classifier: Operating System :: MacOS :: MacOS X
Classifier: Operating System :: Microsoft :: Windows
Classifier: Operating System :: POSIX
Classifier: Programming Language :: Python :: 2
Classifier: Programming Language :: Python :: 2.7
Classifier: Programming Language :: Python :: 3
Classifier: Programming Language :: Python :: 3.6
Classifier: Topic :: Security
Requires-Dist: certifi (>=2019.6.16)
Requires-Dist: chardet (==3.0.4)
Requires-Dist: idna (==2.7)
Requires-Dist: requests (<3.0,>=2.20.0)
Requires-Dist: urllib3 (<1.25,>=1.24.3)
Provides-Extra: dev
Requires-Dist: atomicwrites (==1.2.1) ; extra == 'dev'
Requires-Dist: attrs (==18.2.0) ; extra == 'dev'
Requires-Dist: bleach (>=3.1.2) ; extra == 'dev'
Requires-Dist: certifi (==2018.10.15) ; extra == 'dev'
Requires-Dist: cffi (==1.11.5) ; extra == 'dev'
Requires-Dist: chardet (==3.0.4) ; extra == 'dev'
Requires-Dist: cmarkgfm (==0.4.2) ; extra == 'dev'
Requires-Dist: codacy-coverage (==1.3.11) ; extra == 'dev'
Requires-Dist: coverage (==4.5.1) ; extra == 'dev'
Requires-Dist: docutils (==0.14) ; extra == 'dev'
Requires-Dist: future (==0.16.0) ; extra == 'dev'
Requires-Dist: idna (==2.7) ; extra == 'dev'
Requires-Dist: more-itertools (==4.3.0) ; extra == 'dev'
Requires-Dist: pandoc (==1.0.2) ; extra == 'dev'
Requires-Dist: pkginfo (==1.4.2) ; extra == 'dev'
Requires-Dist: pluggy (==0.8.0) ; extra == 'dev'
Requires-Dist: ply (==3.11) ; extra == 'dev'
Requires-Dist: pockets (==0.7.2) ; extra == 'dev'
Requires-Dist: py (==1.7.0) ; extra == 'dev'
Requires-Dist: pycparser (==2.19) ; extra == 'dev'
Requires-Dist: pygments (==2.2.0) ; extra == 'dev'
Requires-Dist: pypandoc (==1.4) ; extra == 'dev'
Requires-Dist: pytest-cov (==2.6.0) ; extra == 'dev'
Requires-Dist: pytest (==3.9.2) ; extra == 'dev'
Requires-Dist: readme-renderer (==22.0) ; extra == 'dev'
Requires-Dist: requests-mock (==1.5.2) ; extra == 'dev'
Requires-Dist: requests-toolbelt (==0.8.0) ; extra == 'dev'
Requires-Dist: requests (==2.20.0) ; extra == 'dev'
Requires-Dist: six (==1.11.0) ; extra == 'dev'
Requires-Dist: sphinxcontrib-napoleon (==0.6.1) ; extra == 'dev'
Requires-Dist: tqdm (==4.28.1) ; extra == 'dev'
Requires-Dist: twine (==1.12.1) ; extra == 'dev'
Requires-Dist: urllib3 (<1.25,>=1.24.2) ; extra == 'dev'
Requires-Dist: webencodings (==0.5.1) ; extra == 'dev'
Requires-Dist: wheel (==0.32.2) ; extra == 'dev'
